{
  "name": "40 Wall Street",
  "description": "",
  "stories": [
    {
      "description": "",
      "conflict": "40 Wall Street",
      "category": "Active",
      "mediaOutlet": "Bloomberg",
      "link": "https://www.bloomberg.com/graphics/2016-trump-40-wall-street/",
      "sourceDate": "2016-06-22T00:00:00",
      "headline": "Inside Trump’s Most Valuable Tower: Felons, Dictators and Girl Scouts",
      "conflictId": "5",
      "conflictSlug": "40-wall-street",
      "hasEthics": true
    }
  ],
  "ethics": [
    {
      "familyMemberEthics": [
        {
          "ethicsDocuments": [
            {
              "name": "DJT 2016",
              "date": "5/18/2016 12:00:00 AM",
              "link": "https://assets.documentcloud.org/documents/2838696/Trump-2016-Financial-Disclosure.pdf"
            }
          ],
          "ownerships": [
            {
              "owneeId": "33773",
              "owner": "The Donald J. Trump Revocable Trust",
              "percentage": "99.9"
            },
            {
              "owneeId": "33773",
              "owner": "PARC Consulting, Inc.",
              "percentage": "0.1"
            }
          ],
          "familyMember": "Donald Trump",
          "description": "Pres. Trump resigned as a member and president of 40 Wall Development Associates LLC, but retains an ownership interest. The company reportedly has no independent value or income, and is part of other entity structures.",
          "business": "40 Wall Development Associates LLC",
          "conflictStatus": "Active"
        },
        {
          "ethicsDocuments": [
            {
              "name": "DJT 2016",
              "date": "5/18/2016 12:00:00 AM",
              "link": "https://assets.documentcloud.org/documents/2838696/Trump-2016-Financial-Disclosure.pdf"
            },
            {
              "name": "Ethics Document ",
              "date": "7/20/2017 12:00:00 AM",
              "link": "https://www.documentcloud.org/documents/4053458-OGE-Ivanka-20170720.html"
            }
          ],
          "ownerships": [
            {
              "owneeId": "33774",
              "owner": "40 Wall Development Associates LLC",
              "percentage": "100.0"
            }
          ],
          "familyMember": "Donald Trump",
          "description": "Pres. Trump resigned as president of 40 Wall Street Commercial LLC, but retains an ownership interest.",
          "business": "40 Wall Street Commercial LLC (Payroll Company)",
          "conflictStatus": "Active"
        },
        {
          "ethicsDocuments": [
            {
              "name": "DJT 2016",
              "date": "5/18/2016 12:00:00 AM",
              "link": "https://assets.documentcloud.org/documents/2838696/Trump-2016-Financial-Disclosure.pdf"
            }
          ],
          "ownerships": [
            {
              "owneeId": "33776",
              "owner": "40 Wall Development Associates LLC",
              "percentage": "99.9"
            },
            {
              "owneeId": "33776",
              "owner": "40 Wall Street Member Corp",
              "percentage": "0.1"
            }
          ],
          "familyMember": "Donald Trump",
          "description": "Pres. Trump resigned his position from 40 Wall Street LLC, but retains an ownership interest.",
          "business": "40 Wall Street LLC",
          "conflictStatus": "Active"
        },
        {
          "ethicsDocuments": [
            {
              "name": "DJT 2016",
              "date": "5/18/2016 12:00:00 AM",
              "link": "https://assets.documentcloud.org/documents/2838696/Trump-2016-Financial-Disclosure.pdf"
            }
          ],
          "ownerships": [
            {
              "owneeId": "33777",
              "owner": "40 Wall Development Associates LLC",
              "percentage": "100.0"
            }
          ],
          "familyMember": "Donald Trump",
          "description": "Pres. Trump resigned his position from 40 Wall Street Member Corp., but retains an ownership interest. The company reportedly has no independent value or income, and is part of other entity structures.",
          "business": "40 Wall Street Member Corp",
          "conflictStatus": "Active"
        },
        {
          "ethicsDocuments": [
            {
              "name": "DJT 2016",
              "date": "5/18/2016 12:00:00 AM",
              "link": "https://assets.documentcloud.org/documents/2838696/Trump-2016-Financial-Disclosure.pdf"
            },
            {
              "name": "Ethics Document ",
              "date": "7/20/2017 12:00:00 AM",
              "link": "https://www.documentcloud.org/documents/4053458-OGE-Ivanka-20170720.html"
            }
          ],
          "ownerships": [
            {
              "owneeId": "33774",
              "owner": "40 Wall Development Associates LLC",
              "percentage": "100.0"
            }
          ],
          "familyMember": "Ivanka Trump",
          "description": "Ivanka Trump served as Vice President of 40 WALL STREET COMMERCIAL LLC (payroll company) from Aug 1, 2009, until Jan 1, 2017.",
          "business": "40 Wall Street Commercial LLC (Payroll Company)",
          "conflictStatus": "Resolved"
        }
      ],
      "conflictId": "5",
      "conflict": "40 Wall Street",
      "conflictDescription": ""
    }
  ]
}