{
  "name": "Jupiter Golf Club",
  "description": "",
  "stories": [
    {
      "description": "",
      "conflict": "Jupiter Golf Club",
      "category": "Active",
      "mediaOutlet": "Washington Post",
      "link": "https://www.washingtonpost.com/politics/the-three-biggest-surprises-in-the-trump-organizations-financial-filings/2018/05/21/db2f0420-5c94-11e8-9ee3-49d6d4814c4c_story.html?utm_term=.64de8850a39d",
      "sourceDate": "2018-05-21T00:00:00",
      "headline": "The three biggest surprises in the Trump Organization’s financial filings",
      "conflictId": "118",
      "conflictSlug": "jupiter-golf-club",
      "hasEthics": true
    }
  ],
  "ethics": [
    {
      "familyMemberEthics": [
        {
          "ethicsDocuments": [
            {
              "name": "DJT 2016",
              "date": "5/18/2016 12:00:00 AM",
              "link": "https://assets.documentcloud.org/documents/2838696/Trump-2016-Financial-Disclosure.pdf"
            },
            {
              "name": "Ethics Document ",
              "date": "7/20/2017 12:00:00 AM",
              "link": "https://www.documentcloud.org/documents/4053458-OGE-Ivanka-20170720.html"
            }
          ],
          "ownerships": [
            {
              "owneeId": "34521",
              "owner": "DJT Holdings LLC",
              "percentage": "99.0"
            },
            {
              "owneeId": "34521",
              "owner": "Jupiter Golf Club Managing Member Corp.",
              "percentage": "1.0"
            }
          ],
          "familyMember": "Donald Trump",
          "description": "Former president of Jupiter Golf Club LLC (Trump National Golf Club - Jupiter), in which Pres. Trump retains an ownership interest.",
          "business": "Jupiter Golf Club LLC (Trump National Golf Club - Jupiter)",
          "conflictStatus": "Active"
        },
        {
          "ethicsDocuments": [
            {
              "name": "DJT 2016",
              "date": "5/18/2016 12:00:00 AM",
              "link": "https://assets.documentcloud.org/documents/2838696/Trump-2016-Financial-Disclosure.pdf"
            },
            {
              "name": "Ethics Document ",
              "date": "7/20/2017 12:00:00 AM",
              "link": "https://www.documentcloud.org/documents/4053458-OGE-Ivanka-20170720.html"
            }
          ],
          "ownerships": [
            {
              "owneeId": "34523",
              "owner": "DJT Holdings Managing Member LLC",
              "percentage": "100.0"
            }
          ],
          "familyMember": "Donald Trump",
          "description": "Former president/director/chairman of Jupiter Golf Club Managing Member Corp., in which Pres. Trump retains an ownership interest. The company reportedly has no independent value or income, and is part of other entity structures.",
          "business": "Jupiter Golf Club Managing Member Corp (Pass-Thru Company for Jupiter Golf Club LLC (Golf Club))",
          "conflictStatus": "Active"
        },
        {
          "ethicsDocuments": [
            {
              "name": "DJT 2016",
              "date": "5/18/2016 12:00:00 AM",
              "link": "https://assets.documentcloud.org/documents/2838696/Trump-2016-Financial-Disclosure.pdf"
            },
            {
              "name": "Ethics Document ",
              "date": "7/20/2017 12:00:00 AM",
              "link": "https://www.documentcloud.org/documents/4053458-OGE-Ivanka-20170720.html"
            }
          ],
          "ownerships": [
            {
              "owneeId": "34521",
              "owner": "DJT Holdings LLC",
              "percentage": "99.0"
            },
            {
              "owneeId": "34521",
              "owner": "Jupiter Golf Club Managing Member Corp.",
              "percentage": "1.0"
            }
          ],
          "familyMember": "Ivanka Trump",
          "description": "Ivanka Trump served as Executive Vice President of JUPITER GOLF CLUB LLC (golf club) from Sep 1, 2012, until Jan 1, 2017.",
          "business": "Jupiter Golf Club LLC (Trump National Golf Club - Jupiter)",
          "conflictStatus": "Resolved"
        },
        {
          "ethicsDocuments": [
            {
              "name": "DJT 2016",
              "date": "5/18/2016 12:00:00 AM",
              "link": "https://assets.documentcloud.org/documents/2838696/Trump-2016-Financial-Disclosure.pdf"
            },
            {
              "name": "Ethics Document ",
              "date": "7/20/2017 12:00:00 AM",
              "link": "https://www.documentcloud.org/documents/4053458-OGE-Ivanka-20170720.html"
            }
          ],
          "ownerships": [
            {
              "owneeId": "34523",
              "owner": "DJT Holdings Managing Member LLC",
              "percentage": "100.0"
            }
          ],
          "familyMember": "Ivanka Trump",
          "description": "Ivanka Trump served as Executive Vice President of JUPITER GOLF CLUB MANAGING MEMBER CORP (pass-thru company for JUPITER GOLF CLUB LLC (golf club)) from Sep 1, 2012, until Jan 1, 2017.",
          "business": "Jupiter Golf Club Managing Member Corp (Pass-Thru Company for Jupiter Golf Club LLC (Golf Club))",
          "conflictStatus": "Resolved"
        }
      ],
      "conflictId": "118",
      "conflict": "Jupiter Golf Club",
      "conflictDescription": ""
    }
  ]
}