{
  "name": "Nitto World",
  "description": "",
  "familyMembers": [
    "Donald Trump",
    "Ivanka Trump"
  ],
  "stories": [],
  "ethics": [
    {
      "familyMemberEthics": [
        {
          "ethicsDocuments": [
            {
              "name": "DJT 2016",
              "date": "5/18/2016 12:00:00 AM",
              "link": "https://assets.documentcloud.org/documents/2838696/Trump-2016-Financial-Disclosure.pdf"
            }
          ],
          "ownerships": [
            {
              "owneeId": "40599",
              "owner": "SLC Turnberry Limited (Trump Turnberry)",
              "percentage": "100.0"
            }
          ],
          "familyMember": "Donald Trump",
          "description": "Former director of the now-dormant or inactive Nitto World Co., Limited, in which Pres. Trump retains an ownership interest.",
          "business": "Nitto World Co., Limited",
          "conflictStatus": "Active"
        },
        {
          "ethicsDocuments": [
            {
              "name": "Ethics Document ",
              "date": "7/20/2017 12:00:00 AM",
              "link": "https://www.documentcloud.org/documents/4053458-OGE-Ivanka-20170720.html"
            }
          ],
          "ownerships": [],
          "familyMember": "Ivanka Trump",
          "description": "Ivanka Trump served as Director of NITTO WORLD CO., LIMITED (dormant/inactive) from Jun 1, 2014, until Jan 1, 2017.",
          "business": "Nitto World Co., Limited (Dormant/Inactive)",
          "conflictStatus": "Resolved"
        }
      ],
      "conflictId": "133",
      "conflict": "Nitto World",
      "conflictDescription": ""
    }
  ]
}