{
  "name": "THC Baku Hotel Manager Services",
  "description": "",
  "stories": [],
  "ethics": [
    {
      "familyMemberEthics": [
        {
          "ethicsDocuments": [
            {
              "name": "DJT 2016",
              "date": "5/18/2016 12:00:00 AM",
              "link": "https://assets.documentcloud.org/documents/2838696/Trump-2016-Financial-Disclosure.pdf"
            }
          ],
          "ownerships": [
            {
              "owneeId": "40912",
              "owner": "DJT Holdings LLC",
              "percentage": "99.0"
            },
            {
              "owneeId": "40912",
              "owner": "THC Baku Hotel Manager Services Member Corp.",
              "percentage": "1.0"
            }
          ],
          "familyMember": "Donald Trump",
          "description": "Former president/member of THC Baku Hotel Manager Services LLC, in which Pres. Trump retains an ownership interest. The company reportedly has no independent value or income, and exists to hold license deals that are prospective, inactive, or otherwise do not currently have valuable assets or create income.",
          "business": "THC Baku Hotel Manager Services LLC",
          "conflictStatus": "Active"
        },
        {
          "ethicsDocuments": [
            {
              "name": "DJT 2016",
              "date": "5/18/2016 12:00:00 AM",
              "link": "https://assets.documentcloud.org/documents/2838696/Trump-2016-Financial-Disclosure.pdf"
            },
            {
              "name": "Ethics Document ",
              "date": "7/20/2017 12:00:00 AM",
              "link": "https://www.documentcloud.org/documents/4053458-OGE-Ivanka-20170720.html"
            }
          ],
          "ownerships": [
            {
              "owneeId": "40914",
              "owner": "DJT Holdings Managing Member LLC",
              "percentage": "100.0"
            }
          ],
          "familyMember": "Donald Trump",
          "description": "Former director/chairman/president of THC Baku Hotel Manager Services Member Corp., in which Pres. Trump retains an ownership interest. The company reportedly has no independent value or income, and exists to hold license deals that are prospective, inactive, or otherwise do not currently have valuable assets or create income.",
          "business": "THC Baku Hotel Manager Services Member Corp (Pass-Thru Company for THC Baku Hotel Manager Services LLC (Dormant/Inactive))",
          "conflictStatus": "Active"
        },
        {
          "ethicsDocuments": [
            {
              "name": "Ethics Document ",
              "date": "7/20/2017 12:00:00 AM",
              "link": "https://www.documentcloud.org/documents/4053458-OGE-Ivanka-20170720.html"
            }
          ],
          "ownerships": [],
          "familyMember": "Ivanka Trump",
          "description": "Ivanka Trump served as Executive Vice President of THC BAKU HOTEL MANAGER SERVICES LLC (dormant/inactive) from Dec 1, 2014, until Jan 1, 2017.",
          "business": "THC Baku Hotel Manager Services LLC (Dormant/Inactive)",
          "conflictStatus": "Resolved"
        },
        {
          "ethicsDocuments": [
            {
              "name": "DJT 2016",
              "date": "5/18/2016 12:00:00 AM",
              "link": "https://assets.documentcloud.org/documents/2838696/Trump-2016-Financial-Disclosure.pdf"
            },
            {
              "name": "Ethics Document ",
              "date": "7/20/2017 12:00:00 AM",
              "link": "https://www.documentcloud.org/documents/4053458-OGE-Ivanka-20170720.html"
            }
          ],
          "ownerships": [
            {
              "owneeId": "40914",
              "owner": "DJT Holdings Managing Member LLC",
              "percentage": "100.0"
            }
          ],
          "familyMember": "Ivanka Trump",
          "description": "Ivanka Trump served as Executive Vice President of THC BAKU HOTEL MANAGER SERVICES MEMBER CORP (pass-thru company for THC BAKU HOTEL MANAGER SERVICES LLC (dormant/inactive)) from Dec 1, 2014, until Jan 1, 2017.",
          "business": "THC Baku Hotel Manager Services Member Corp (Pass-Thru Company for THC Baku Hotel Manager Services LLC (Dormant/Inactive))",
          "conflictStatus": "Resolved"
        }
      ],
      "conflictId": "165",
      "conflict": "THC Baku Hotel Manager Services",
      "conflictDescription": ""
    }
  ]
}