{
  "familyMemberBusinessWithEthicsList": [
    {
      "ethicsDocuments": [
        {
          "name": "DJT 2016",
          "date": "5/18/2016 12:00:00 AM",
          "link": "https://assets.documentcloud.org/documents/2838696/Trump-2016-Financial-Disclosure.pdf"
        }
      ],
      "ownerships": [
        {
          "owneeId": "277",
          "owner": "DJT Holdings LLC",
          "percentage": "99"
        },
        {
          "owneeId": "277",
          "owner": "THC Qatar Hotel Manager Member Corp.",
          "percentage": "1"
        }
      ],
      "familyMember": "Donald Trump",
      "description": "Former member/president of THC Qatar Hotel Manager LLC, which reportedly was dissolved on Jan. 26, 2017. Pres. Trump held an ownership interest in the company at the time.",
      "business": "THC Qatar Hotel Manager LLC",
      "conflictStatus": "Resolved"
    },
    {
      "ethicsDocuments": [
        {
          "name": "DJT 2016",
          "date": "5/18/2016 12:00:00 AM",
          "link": "https://assets.documentcloud.org/documents/2838696/Trump-2016-Financial-Disclosure.pdf"
        }
      ],
      "ownerships": [
        {
          "owneeId": "276",
          "owner": "DJT Holdings Managing Member LLC",
          "percentage": "100"
        }
      ],
      "familyMember": "Donald Trump",
      "description": "Former chairman/director/president of THC Qatar Hotel Manager Member Corp., which reportedly was dissolved on Jan. 26, 2017. Pres. Trump held an ownership interest in the company at the time.",
      "business": "THC Qatar Hotel Manager Member Corp.",
      "conflictStatus": "Resolved"
    }
  ],
  "conflictId": "179",
  "conflict": "THC Qatar Hotel Manager",
  "conflictDescription": ""
}