{
  "familyMemberBusinessWithEthicsList": [
    {
      "ethicsDocuments": [
        {
          "name": "2016 Office of Government Ethics Form 278e",
          "date": "5/18/2016 12:00:00 AM",
          "link": "https://assets.documentcloud.org/documents/2838696/Trump-2016-Financial-Disclosure.pdf"
        }
      ],
      "ownerships": [],
      "familyMember": "Donald Trump",
      "description": "Former director of Golf Recreation Scotland Limited, of which Pres. Trump retains an ownership interest. The company reportedly has no independent value or income, and is part of other entity structures.",
      "business": "Golf Recreation Scotland Limited",
      "conflictStatus": "Active"
    },
    {
      "ethicsDocuments": [
        {
          "name": "2016 Office of Government Ethics Form 278e",
          "date": "5/18/2016 12:00:00 AM",
          "link": "https://assets.documentcloud.org/documents/2838696/Trump-2016-Financial-Disclosure.pdf"
        }
      ],
      "ownerships": [],
      "familyMember": "Donald Trump",
      "description": "Former director/chairman of SLC Turnberry Limited (Trump Turnberry), in which Pres. Trump retains an ownership interest.",
      "business": "Slc Turnberry Limited (Trump Turnberry)",
      "conflictStatus": "Active"
    },
    {
      "ethicsDocuments": [
        {
          "name": "2016 Office of Government Ethics Form 278e",
          "date": "5/18/2016 12:00:00 AM",
          "link": "https://assets.documentcloud.org/documents/2838696/Trump-2016-Financial-Disclosure.pdf"
        }
      ],
      "ownerships": [],
      "familyMember": "Donald Trump",
      "description": "Former president of Turnberry Scotland LLC, in which Pres. Trump retains an ownership interest. The company reportedly has no independent value or income, and is part of other entity structures.",
      "business": "Turnberry Scotland LLC",
      "conflictStatus": "Active"
    },
    {
      "ethicsDocuments": [
        {
          "name": "2016 Office of Government Ethics Form 278e",
          "date": "5/18/2016 12:00:00 AM",
          "link": "https://assets.documentcloud.org/documents/2838696/Trump-2016-Financial-Disclosure.pdf"
        }
      ],
      "ownerships": [],
      "familyMember": "Donald Trump",
      "description": "Former director/chairman/president of Turnberry Scotland Managing Member Corp., in which Pres. Trump retains an ownership interest. The company reportedly has no independent value or income, and is part of other entity structures.",
      "business": "Turnberry Scotland Managing Member Corp",
      "conflictStatus": "Active"
    }
  ],
  "conflictId": "358",
  "conflict": "Trump Turnberry",
  "conflictDescription": ""
}