{
  "familyMemberBusinessWithEthicsList": [
    {
      "ethicsDocuments": [
        {
          "name": "2016 Office of Government Ethics Form 278e",
          "date": "5/18/2016 12:00:00 AM",
          "link": "https://assets.documentcloud.org/documents/2838696/Trump-2016-Financial-Disclosure.pdf"
        }
      ],
      "ownerships": [],
      "familyMember": "Donald Trump",
      "description": "Former manager of the now-dormant or inactive The Donald J. Trump Company LLC, in which Pres. Trump retains an ownership interest.",
      "business": "The Donald J. Trump Company LLC",
      "conflictStatus": "Active"
    }
  ],
  "conflictId": "44",
  "conflict": "Donald J. Trump Company",
  "conflictDescription": "TEST DESCRIPTION FOR THE CONFLICT (Friendly Name): Donald J. Trump Company"
}